Phase 1 Learning/MUX/MUX_2_1_example.v
module MUX_2_1 (S0,A,B,Y);
    
input S0,A,B;
output Y;

assign Y=((~S0)&A)+(S0&B);

endmodule

Phase 1 Learning/MUX/MUX_8_1_structural.v
`include "MUX_2_1_example.v"

module MUX_8_1_str (
input I0,I1,I2,I3,I4,I5,I6,I7,
input S0,S1,S2,
output Y 
);

wire t1,t2,t3,t4,t5,t6;

//level 1
MUX_2_1 m1 (S0,I0,I1,t1);
MUX_2_1 m2 (S0,I2,I3,t2);
MUX_2_1 m3 (S0,I4,I5,t3);
MUX_2_1 m4 (S0,I6,I7,t4);

//level 2
MUX_2_1 m5 (S1,t1,t2,t5);
MUX_2_1 m6 (S1,t3,t4,t6);

//level 3

MUX_2_1 m7 (S2,t5,t6,Y);
    
endmodule

Phase 1 Learning/MUX/MUX_8_1_structural_tb.v
`timescale 1ns/1ns
`include "MUX_8_1_structural.v"

module MUX_8_1_structural_tb;

reg I0,I1,I2,I3,I4,I5,I6,I7;
reg S0,S1,S2;
wire Y;

MUX_8_1_str uut(I0,I1,I2,I3,I4,I5,I6,I7,S0,S1,S2,Y);

initial begin
    $display("Time\tS2 S1 S0 | I0 I1 I2 I3 I4 I5 I6 I7 | Y");
    $monitor("%g\t%b  %b  %b  | %b  %b  %b  %b  %b  %b  %b  %b  | %b",$time,S2,S1,S0,I0,I1,I2,I3,I4,I5,I6,I7,Y);
end

initial begin
    S0=0; S1=0; S2=0; I0=0; I1=0; I2=0; I3=0; I4=0; I5=0; I6=0; I7=0;
end

always #1 I7=~I7;
always #2 I6=~I6;
always #4 I5=~I5;
always #8 I4=~I4;
always #16 I3=~I3;
always #32 I2=~I2;
always #64 I1=~I1;
always #128 I0=~I0;
always #256 S0=~S0;
always #512 S1=~S1;
always #1024 S2=~S2;

initial begin
    #2100 $finish;
end

initial begin
    $dumpfile("MUX_8_1_structural.vcd");
    $dumpvars(0,MUX_8_1_structural_tb);
end
    
endmodule

Phase 1 Learning/MUX/MUX_8_1_structural.vcd
$date
	Sat Apr 18 01:12:15 2026
$end
$version
	Icarus Verilog
$end
$timescale
	1ns
$end
$scope module MUX_8_1_structural_tb $end
$var wire 1 ! Y $end
$var reg 1 " I0 $end
$var reg 1 # I1 $end
$var reg 1 $ I2 $end
$var reg 1 % I3 $end
$var reg 1 & I4 $end
$var reg 1 ' I5 $end
$var reg 1 ( I6 $end
$var reg 1 ) I7 $end
$var reg 1 * S0 $end
$var reg 1 + S1 $end
$var reg 1 , S2 $end
$scope module uut $end
$var wire 1 " I0 $end
$var wire 1 # I1 $end
$var wire 1 $ I2 $end
$var wire 1 % I3 $end
$var wire 1 & I4 $end
$var wire 1 ' I5 $end
$var wire 1 ( I6 $end
$var wire 1 ) I7 $end
$var wire 1 * S0 $end
$var wire 1 + S1 $end
$var wire 1 , S2 $end
$var wire 1 - t6 $end
$var wire 1 . t5 $end
$var wire 1 / t4 $end
$var wire 1 0 t3 $end
$var wire 1 1 t2 $end
$var wire 1 2 t1 $end
$var wire 1 ! Y $end
$scope module m1 $end
$var wire 1 " A $end
$var wire 1 # B $end
$var wire 1 * S0 $end
$var wire 1 2 Y $end
$upscope $end
$scope module m2 $end
$var wire 1 $ A $end
$var wire 1 % B $end
$var wire 1 * S0 $end
$var wire 1 1 Y $end
$upscope $end
$scope module m3 $end
$var wire 1 & A $end
$var wire 1 ' B $end
$var wire 1 * S0 $end
$var wire 1 0 Y $end
$upscope $end
$scope module m4 $end
$var wire 1 ( A $end
$var wire 1 ) B $end
$var wire 1 * S0 $end
$var wire 1 / Y $end
$upscope $end
$scope module m5 $end
$var wire 1 2 A $end
$var wire 1 1 B $end
$var wire 1 + S0 $end
$var wire 1 . Y $end
$upscope $end
$scope module m6 $end
$var wire 1 0 A $end
$var wire 1 / B $end
$var wire 1 + S0 $end
$var wire 1 - Y $end
$upscope $end
$scope module m7 $end
$var wire 1 . A $end
$var wire 1 - B $end
$var wire 1 , S0 $end
$var wire 1 ! Y $end
$upscope $end
$upscope $end
$upscope $end
$enddefinitions $end
$comment Show the parameter values. $end
$dumpall
$end
#0
$dumpvars
02
01
00
0/
0.
0-
0,
0+
0*
0)
0(
0'
0&
0%
0$
0#
0"
0!
$end
#1
1)
#2
1/
0)
1(
#3
1)
#4
0/
0)
0(
1'
#5
1)
#6
1/
0)
1(
#7
1)
#8
1-
0/
10
0)
0(
0'
1&
#9
1)
#10
1/
0)
1(
#11
1)
#12
0/
0)
0(
1'
#13
1)
#14
1/
0)
1(
#15
1)
#16
0-
0/
00
0)
0(
0'
0&
1%
#17
1)
#18
1/
0)
1(
#19
1)
#20
0/
0)
0(
1'
#21
1)
#22
1/
0)
1(
#23
1)
#24
1-
0/
10
0)
0(
0'
1&
#25
1)
#26
1/
0)
1(
#27
1)
#28
0/
0)
0(
1'
#29
1)
#30
1/
0)
1(
#31
1)
#32
0-
0/
00
11
0)
0(
0'
0&
0%
1$
#33
1)
#34
1/
0)
1(
#35
1)
#36
0/
0)
0(
1'
#37
1)
#38
1/
0)
1(
#39
1)
#40
1-
0/
10
0)
0(
0'
1&
#41
1)
#42
1/
0)
1(
#43
1)
#44
0/
0)
0(
1'
#45
1)
#46
1/
0)
1(
#47
1)
#48
0-
0/
00
0)
0(
0'
0&
1%
#49
1)
#50
1/
0)
1(
#51
1)
#52
0/
0)
0(
1'
#53
1)
#54
1/
0)
1(
#55
1)
#56
1-
0/
10
0)
0(
0'
1&
#57
1)
#58
1/
0)
1(
#59
1)
#60
0/
0)
0(
1'
#61
1)
#62
1/
0)
1(
#63
1)
#64
0-
0/
00
01
0)
0(
0'
0&
0%
0$
1#
#65
1)
#66
1/
0)
1(
#67
1)
#68
0/
0)
0(
1'
#69
1)
#70
1/
0)
1(
#71
1)
#72
1-
0/
10
0)
0(
0'
1&
#73
1)
#74
1/
0)
1(
#75
1)
#76
0/
0)
0(
1'
#77
1)
#78
1/
0)
1(
#79
1)
#80
0-
0/
00
0)
0(
0'
0&
1%
#81
1)
#82
1/
0)
1(
#83
1)
#84
0/
0)
0(
1'
#85
1)
#86
1/
0)
1(
#87
1)
#88
1-
0/
10
0)
0(
0'
1&
#89
1)
#90
1/
0)
1(
#91
1)
#92
0/
0)
0(
1'
#93
1)
#94
1/
0)
1(
#95
1)
#96
0-
0/
00
11
0)
0(
0'
0&
0%
1$
#97
1)
#98
1/
0)
1(
#99
1)
#100
0/
0)
0(
1'
#101
1)
#102
1/
0)
1(
#103
1)
#104
1-
0/
10
0)
0(
0'
1&
#105
1)
#106
1/
0)
1(
#107
1)
#108
0/
0)
0(
1'
#109
1)
#110
1/
0)
1(
#111
1)
#112
0-
0/
00
0)
0(
0'
0&
1%
#113
1)
#114
1/
0)
1(
#115
1)
#116
0/
0)
0(
1'
#117
1)
#118
1/
0)
1(
#119
1)
#120
1-
0/
10
0)
0(
0'
1&
#121
1)
#122
1/
0)
1(
#123
1)
#124
0/
0)
0(
1'
#125
1)
#126
1/
0)
1(
#127
1)
#128
1!
0-
1.
0/
00
01
12
0)
0(
0'
0&
0%
0$
0#
1"
#129
1)
#130
1/
0)
1(
#131
1)
#132
0/
0)
0(
1'
#133
1)
#134
1/
0)
1(
#135
1)
#136
1-
0/
10
0)
0(
0'
1&
#137
1)
#138
1/
0)
1(
#139
1)
#140
0/
0)
0(
1'
#141
1)
#142
1/
0)
1(
#143
1)
#144
0-
0/
00
0)
0(
0'
0&
1%
#145
1)
#146
1/
0)
1(
#147
1)
#148
0/
0)
0(
1'
#149
1)
#150
1/
0)
1(
#151
1)
#152
1-
0/
10
0)
0(
0'
1&
#153
1)
#154
1/
0)
1(
#155
1)
#156
0/
0)
0(
1'
#157
1)
#158
1/
0)
1(
#159
1)
#160
0-
0/
00
11
0)
0(
0'
0&
0%
1$
#161
1)
#162
1/
0)
1(
#163
1)
#164
0/
0)
0(
1'
#165
1)
#166
1/
0)
1(
#167
1)
#168
1-
0/
10
0)
0(
0'
1&
#169
1)
#170
1/
0)
1(
#171
1)
#172
0/
0)
0(
1'
#173
1)
#174
1/
0)
1(
#175
1)
#176
0-
0/
00
0)
0(
0'
0&
1%
#177
1)
#178
1/
0)
1(
#179
1)
#180
0/
0)
0(
1'
#181
1)
#182
1/
0)
1(
#183
1)
#184
1-
0/
10
0)
0(
0'
1&
#185
1)
#186
1/
0)
1(
#187
1)
#188
0/
0)
0(
1'
#189
1)
#190
1/
0)
1(
#191
1)
#192
0-
0/
00
01
0)
0(
0'
0&
0%
0$
1#
#193
1)
#194
1/
0)
1(
#195
1)
#196
0/
0)
0(
1'
#197
1)
#198
1/
0)
1(
#199
1)
#200
1-
0/
10
0)
0(
0'
1&
#201
1)
#202
1/
0)
1(
#203
1)
#204
0/
0)
0(
1'
#205
1)
#206
1/
0)
1(
#207
1)
#208
0-
0/
00
0)
0(
0'
0&
1%
#209
1)
#210
1/
0)
1(
#211
1)
#212
0/
0)
0(
1'
#213
1)
#214
1/
0)
1(
#215
1)
#216
1-
0/
10
0)
0(
0'
1&
#217
1)
#218
1/
0)
1(
#219
1)
#220
0/
0)
0(
1'
#221
1)
#222
1/
0)
1(
#223
1)
#224
0-
0/
00
11
0)
0(
0'
0&
0%
1$
#225
1)
#226
1/
0)
1(
#227
1)
#228
0/
0)
0(
1'
#229
1)
#230
1/
0)
1(
#231
1)
#232
1-
0/
10
0)
0(
0'
1&
#233
1)
#234
1/
0)
1(
#235
1)
#236
0/
0)
0(
1'
#237
1)
#238
1/
0)
1(
#239
1)
#240
0-
0/
00
0)
0(
0'
0&
1%
#241
1)
#242
1/
0)
1(
#243
1)
#244
0/
0)
0(
1'
#245
1)
#246
1/
0)
1(
#247
1)
#248
1-
0/
10
0)
0(
0'
1&
#249
1)
#250
1/
0)
1(
#251
1)
#252
0/
0)
0(
1'
#253
1)
#254
1/
0)
1(
#255
1)
#256
0!
0-
0.
0/
00
01
02
0)
0(
0'
0&
0%
0$
0#
0"
1*
#257
1/
1)
#258
0/
0)
1(
#259
1/
1)
#260
1-
0/
10
0)
0(
1'
#261
1/
1)
#262
0/
0)
1(
#263
1/
1)
#264
0-
0/
00
0)
0(
0'
1&
#265
1/
1)
#266
0/
0)
1(
#267
1/
1)
#268
1-
0/
10
0)
0(
1'
#269
1/
1)
#270
0/
0)
1(
#271
1/
1)
#272
0-
0/
00
11
0)
0(
0'
0&
1%
#273
1/
1)
#274
0/
0)
1(
#275
1/
1)
#276
1-
0/
10
0)
0(
1'
#277
1/
1)
#278
0/
0)
1(
#279
1/
1)
#280
0-
0/
00
0)
0(
0'
1&
#281
1/
1)
#282
0/
0)
1(
#283
1/
1)
#284
1-
0/
10
0)
0(
1'
#285
1/
1)
#286
0/
0)
1(
#287
1/
1)
#288
0-
0/
00
01
0)
0(
0'
0&
0%
1$
#289
1/
1)
#290
0/
0)
1(
#291
1/
1)
#292
1-
0/
10
0)
0(
1'
#293
1/
1)
#294
0/
0)
1(
#295
1/
1)
#296
0-
0/
00
0)
0(
0'
1&
#297
1/
1)
#298
0/
0)
1(
#299
1/
1)
#300
1-
0/
10
0)
0(
1'
#301
1/
1)
#302
0/
0)
1(
#303
1/
1)
#304
0-
0/
00
11
0)
0(
0'
0&
1%
#305
1/
1)
#306
0/
0)
1(
#307
1/
1)
#308
1-
0/
10
0)
0(
1'
#309
1/
1)
#310
0/
0)
1(
#311
1/
1)
#312
0-
0/
00
0)
0(
0'
1&
#313
1/
1)
#314
0/
0)
1(
#315
1/
1)
#316
1-
0/
10
0)
0(
1'
#317
1/
1)
#318
0/
0)
1(
#319
1/
1)
#320
1!
0-
1.
0/
00
01
12
0)
0(
0'
0&
0%
0$
1#
#321
1/
1)
#322
0/
0)
1(
#323
1/
1)
#324
1-
0/
10
0)
0(
1'
#325
1/
1)
#326
0/
0)
1(
#327
1/
1)
#328
0-
0/
00
0)
0(
0'
1&
#329
1/
1)
#330
0/
0)
1(
#331
1/
1)
#332
1-
0/
10
0)
0(
1'
#333
1/
1)
#334
0/
0)
1(
#335
1/
1)
#336
0-
0/
00
11
0)
0(
0'
0&
1%
#337
1/
1)
#338
0/
0)
1(
#339
1/
1)
#340
1-
0/
10
0)
0(
1'
#341
1/
1)
#342
0/
0)
1(
#343
1/
1)
#344
0-
0/
00
0)
0(
0'
1&
#345
1/
1)
#346
0/
0)
1(
#347
1/
1)
#348
1-
0/
10
0)
0(
1'
#349
1/
1)
#350
0/
0)
1(
#351
1/
1)
#352
0-
0/
00
01
0)
0(
0'
0&
0%
1$
#353
1/
1)
#354
0/
0)
1(
#355
1/
1)
#356
1-
0/
10
0)
0(
1'
#357
1/
1)
#358
0/
0)
1(
#359
1/
1)
#360
0-
0/
00
0)
0(
0'
1&
#361
1/
1)
#362
0/
0)
1(
#363
1/
1)
#364
1-
0/
10
0)
0(
1'
#365
1/
1)
#366
0/
0)
1(
#367
1/
1)
#368
0-
0/
00
11
0)
0(
0'
0&
1%
#369
1/
1)
#370
0/
0)
1(
#371
1/
1)
#372
1-
0/
10
0)
0(
1'
#373
1/
1)
#374
0/
0)
1(
#375
1/
1)
#376
0-
0/
00
0)
0(
0'
1&
#377
1/
1)
#378
0/
0)
1(
#379
1/
1)
#380
1-
0/
10
0)
0(
1'
#381
1/
1)
#382
0/
0)
1(
#383
1/
1)
#384
0!
0-
0.
0/
00
01
02
0)
0(
0'
0&
0%
0$
0#
1"
#385
1/
1)
#386
0/
0)
1(
#387
1/
1)
#388
1-
0/
10
0)
0(
1'
#389
1/
1)
#390
0/
0)
1(
#391
1/
1)
#392
0-
0/
00
0)
0(
0'
1&
#393
1/
1)
#394
0/
0)
1(
#395
1/
1)
#396
1-
0/
10
0)
0(
1'
#397
1/
1)
#398
0/
0)
1(
#399
1/
1)
#400
0-
0/
00
11
0)
0(
0'
0&
1%
#401
1/
1)
#402
0/
0)
1(
#403
1/
1)
#404
1-
0/
10
0)
0(
1'
#405
1/
1)
#406
0/
0)
1(
#407
1/
1)
#408
0-
0/
00
0)
0(
0'
1&
#409
1/
1)
#410
0/
0)
1(
#411
1/
1)
#412
1-
0/
10
0)
0(
1'
#413
1/
1)
#414
0/
0)
1(
#415
1/
1)
#416
0-
0/
00
01
0)
0(
0'
0&
0%
1$
#417
1/
1)
#418
0/
0)
1(
#419
1/
1)
#420
1-
0/
10
0)
0(
1'
#421
1/
1)
#422
0/
0)
1(
#423
1/
1)
#424
0-
0/
00
0)
0(
0'
1&
#425
1/
1)
#426
0/
0)
1(
#427
1/
1)
#428
1-
0/
10
0)
0(
1'
#429
1/
1)
#430
0/
0)
1(
#431
1/
1)
#432
0-
0/
00
11
0)
0(
0'
0&
1%
#433
1/
1)
#434
0/
0)
1(
#435
1/
1)
#436
1-
0/
10
0)
0(
1'
#437
1/
1)
#438
0/
0)
1(
#439
1/
1)
#440
0-
0/
00
0)
0(
0'
1&
#441
1/
1)
#442
0/
0)
1(
#443
1/
1)
#444
1-
0/
10
0)
0(
1'
#445
1/
1)
#446
0/
0)
1(
#447
1/
1)
#448
1!
0-
1.
0/
00
01
12
0)
0(
0'
0&
0%
0$
1#
#449
1/
1)
#450
0/
0)
1(
#451
1/
1)
#452
1-
0/
10
0)
0(
1'
#453
1/
1)
#454
0/
0)
1(
#455
1/
1)
#456
0-
0/
00
0)
0(
0'
1&
#457
1/
1)
#458
0/
0)
1(
#459
1/
1)
#460
1-
0/
10
0)
0(
1'
#461
1/
1)
#462
0/
0)
1(
#463
1/
1)
#464
0-
0/
00
11
0)
0(
0'
0&
1%
#465
1/
1)
#466
0/
0)
1(
#467
1/
1)
#468
1-
0/
10
0)
0(
1'
#469
1/
1)
#470
0/
0)
1(
#471
1/
1)
#472
0-
0/
00
0)
0(
0'
1&
#473
1/
1)
#474
0/
0)
1(
#475
1/
1)
#476
1-
0/
10
0)
0(
1'
#477
1/
1)
#478
0/
0)
1(
#479
1/
1)
#480
0-
0/
00
01
0)
0(
0'
0&
0%
1$
#481
1/
1)
#482
0/
0)
1(
#483
1/
1)
#484
1-
0/
10
0)
0(
1'
#485
1/
1)
#486
0/
0)
1(
#487
1/
1)
#488
0-
0/
00
0)
0(
0'
1&
#489
1/
1)
#490
0/
0)
1(
#491
1/
1)
#492
1-
0/
10
0)
0(
1'
#493
1/
1)
#494
0/
0)
1(
#495
1/
1)
#496
0-
0/
00
11
0)
0(
0'
0&
1%
#497
1/
1)
#498
0/
0)
1(
#499
1/
1)
#500
1-
0/
10
0)
0(
1'
#501
1/
1)
#502
0/
0)
1(
#503
1/
1)
#504
0-
0/
00
0)
0(
0'
1&
#505
1/
1)
#506
0/
0)
1(
#507
1/
1)
#508
1-
0/
10
0)
0(
1'
#509
1/
1)
#510
0/
0)
1(
#511
1/
1)
#512
0!
02
01
00
0/
0.
0-
0)
0(
0'
0&
0%
0$
0#
0"
0*
1+
#513
1)
#514
1-
1/
0)
1(
#515
1)
#516
0-
0/
0)
0(
1'
#517
1)
#518
1-
1/
0)
1(
#519
1)
#520
0-
0/
10
0)
0(
0'
1&
#521
1)
#522
1-
1/
0)
1(
#523
1)
#524
0-
0/
0)
0(
1'
#525
1)
#526
1-
1/
0)
1(
#527
1)
#528
0-
0/
00
0)
0(
0'
0&
1%
#529
1)
#530
1-
1/
0)
1(
#531
1)
#532
0-
0/
0)
0(
1'
#533
1)
#534
1-
1/
0)
1(
#535
1)
#536
0-
0/
10
0)
0(
0'
1&
#537
1)
#538
1-
1/
0)
1(
#539
1)
#540
0-
0/
0)
0(
1'
#541
1)
#542
1-
1/
0)
1(
#543
1)
#544
1!
0-
1.
0/
00
11
0)
0(
0'
0&
0%
1$
#545
1)
#546
1-
1/
0)
1(
#547
1)
#548
0-
0/
0)
0(
1'
#549
1)
#550
1-
1/
0)
1(
#551
1)
#552
0-
0/
10
0)
0(
0'
1&
#553
1)
#554
1-
1/
0)
1(
#555
1)
#556
0-
0/
0)
0(
1'
#557
1)
#558
1-
1/
0)
1(
#559
1)
#560
0-
0/
00
0)
0(
0'
0&
1%
#561
1)
#562
1-
1/
0)
1(
#563
1)
#564
0-
0/
0)
0(
1'
#565
1)
#566
1-
1/
0)
1(
#567
1)
#568
0-
0/
10
0)
0(
0'
1&
#569
1)
#570
1-
1/
0)
1(
#571
1)
#572
0-
0/
0)
0(
1'
#573
1)
#574
1-
1/
0)
1(
#575
1)
#576
0!
0-
0.
0/
00
01
0)
0(
0'
0&
0%
0$
1#
#577
1)
#578
1-
1/
0)
1(
#579
1)
#580
0-
0/
0)
0(
1'
#581
1)
#582
1-
1/
0)
1(
#583
1)
#584
0-
0/
10
0)
0(
0'
1&
#585
1)
#586
1-
1/
0)
1(
#587
1)
#588
0-
0/
0)
0(
1'
#589
1)
#590
1-
1/
0)
1(
#591
1)
#592
0-
0/
00
0)
0(
0'
0&
1%
#593
1)
#594
1-
1/
0)
1(
#595
1)
#596
0-
0/
0)
0(
1'
#597
1)
#598
1-
1/
0)
1(
#599
1)
#600
0-
0/
10
0)
0(
0'
1&
#601
1)
#602
1-
1/
0)
1(
#603
1)
#604
0-
0/
0)
0(
1'
#605
1)
#606
1-
1/
0)
1(
#607
1)
#608
1!
0-
1.
0/
00
11
0)
0(
0'
0&
0%
1$
#609
1)
#610
1-
1/
0)
1(
#611
1)
#612
0-
0/
0)
0(
1'
#613
1)
#614
1-
1/
0)
1(
#615
1)
#616
0-
0/
10
0)
0(
0'
1&
#617
1)
#618
1-
1/
0)
1(
#619
1)
#620
0-
0/
0)
0(
1'
#621
1)
#622
1-
1/
0)
1(
#623
1)
#624
0-
0/
00
0)
0(
0'
0&
1%
#625
1)
#626
1-
1/
0)
1(
#627
1)
#628
0-
0/
0)
0(
1'
#629
1)
#630
1-
1/
0)
1(
#631
1)
#632
0-
0/
10
0)
0(
0'
1&
#633
1)
#634
1-
1/
0)
1(
#635
1)
#636
0-
0/
0)
0(
1'
#637
1)
#638
1-
1/
0)
1(
#639
1)
#640
0!
0-
0.
0/
00
01
12
0)
0(
0'
0&
0%
0$
0#
1"
#641
1)
#642
1-
1/
0)
1(
#643
1)
#644
0-
0/
0)
0(
1'
#645
1)
#646
1-
1/
0)
1(
#647
1)
#648
0-
0/
10
0)
0(
0'
1&
#649
1)
#650
1-
1/
0)
1(
#651
1)
#652
0-
0/
0)
0(
1'
#653
1)
#654
1-
1/
0)
1(
#655
1)
#656
0-
0/
00
0)
0(
0'
0&
1%
#657
1)
#658
1-
1/
0)
1(
#659
1)
#660
0-
0/
0)
0(
1'
#661
1)
#662
1-
1/
0)
1(
#663
1)
#664
0-
0/
10
0)
0(
0'
1&
#665
1)
#666
1-
1/
0)
1(
#667
1)
#668
0-
0/
0)
0(
1'
#669
1)
#670
1-
1/
0)
1(
#671
1)
#672
1!
0-
1.
0/
00
11
0)
0(
0'
0&
0%
1$
#673
1)
#674
1-
1/
0)
1(
#675
1)
#676
0-
0/
0)
0(
1'
#677
1)
#678
1-
1/
0)
1(
#679
1)
#680
0-
0/
10
0)
0(
0'
1&
#681
1)
#682
1-
1/
0)
1(
#683
1)
#684
0-
0/
0)
0(
1'
#685
1)
#686
1-
1/
0)
1(
#687
1)
#688
0-
0/
00
0)
0(
0'
0&
1%
#689
1)
#690
1-
1/
0)
1(
#691
1)
#692
0-
0/
0)
0(
1'
#693
1)
#694
1-
1/
0)
1(
#695
1)
#696
0-
0/
10
0)
0(
0'
1&
#697
1)
#698
1-
1/
0)
1(
#699
1)
#700
0-
0/
0)
0(
1'
#701
1)
#702
1-
1/
0)
1(
#703
1)
#704
0!
0-
0.
0/
00
01
0)
0(
0'
0&
0%
0$
1#
#705
1)
#706
1-
1/
0)
1(
#707
1)
#708
0-
0/
0)
0(
1'
#709
1)
#710
1-
1/
0)
1(
#711
1)
#712
0-
0/
10
0)
0(
0'
1&
#713
1)
#714
1-
1/
0)
1(
#715
1)
#716
0-
0/
0)
0(
1'
#717
1)
#718
1-
1/
0)
1(
#719
1)
#720
0-
0/
00
0)
0(
0'
0&
1%
#721
1)
#722
1-
1/
0)
1(
#723
1)
#724
0-
0/
0)
0(
1'
#725
1)
#726
1-
1/
0)
1(
#727
1)
#728
0-
0/
10
0)
0(
0'
1&
#729
1)
#730
1-
1/
0)
1(
#731
1)
#732
0-
0/
0)
0(
1'
#733
1)
#734
1-
1/
0)
1(
#735
1)
#736
1!
0-
1.
0/
00
11
0)
0(
0'
0&
0%
1$
#737
1)
#738
1-
1/
0)
1(
#739
1)
#740
0-
0/
0)
0(
1'
#741
1)
#742
1-
1/
0)
1(
#743
1)
#744
0-
0/
10
0)
0(
0'
1&
#745
1)
#746
1-
1/
0)
1(
#747
1)
#748
0-
0/
0)
0(
1'
#749
1)
#750
1-
1/
0)
1(
#751
1)
#752
0-
0/
00
0)
0(
0'
0&
1%
#753
1)
#754
1-
1/
0)
1(
#755
1)
#756
0-
0/
0)
0(
1'
#757
1)
#758
1-
1/
0)
1(
#759
1)
#760
0-
0/
10
0)
0(
0'
1&
#761
1)
#762
1-
1/
0)
1(
#763
1)
#764
0-
0/
0)
0(
1'
#765
1)
#766
1-
1/
0)
1(
#767
1)
#768
0!
0-
0.
0/
00
01
02
0)
0(
0'
0&
0%
0$
0#
0"
1*
#769
1-
1/
1)
#770
0-
0/
0)
1(
#771
1-
1/
1)
#772
0-
0/
10
0)
0(
1'
#773
1-
1/
1)
#774
0-
0/
0)
1(
#775
1-
1/
1)
#776
0-
0/
00
0)
0(
0'
1&
#777
1-
1/
1)
#778
0-
0/
0)
1(
#779
1-
1/
1)
#780
0-
0/
10
0)
0(
1'
#781
1-
1/
1)
#782
0-
0/
0)
1(
#783
1-
1/
1)
#784
1!
0-
1.
0/
00
11
0)
0(
0'
0&
1%
#785
1-
1/
1)
#786
0-
0/
0)
1(
#787
1-
1/
1)
#788
0-
0/
10
0)
0(
1'
#789
1-
1/
1)
#790
0-
0/
0)
1(
#791
1-
1/
1)
#792
0-
0/
00
0)
0(
0'
1&
#793
1-
1/
1)
#794
0-
0/
0)
1(
#795
1-
1/
1)
#796
0-
0/
10
0)
0(
1'
#797
1-
1/
1)
#798
0-
0/
0)
1(
#799
1-
1/
1)
#800
0!
0-
0.
0/
00
01
0)
0(
0'
0&
0%
1$
#801
1-
1/
1)
#802
0-
0/
0)
1(
#803
1-
1/
1)
#804
0-
0/
10
0)
0(
1'
#805
1-
1/
1)
#806
0-
0/
0)
1(
#807
1-
1/
1)
#808
0-
0/
00
0)
0(
0'
1&
#809
1-
1/
1)
#810
0-
0/
0)
1(
#811
1-
1/
1)
#812
0-
0/
10
0)
0(
1'
#813
1-
1/
1)
#814
0-
0/
0)
1(
#815
1-
1/
1)
#816
1!
0-
1.
0/
00
11
0)
0(
0'
0&
1%
#817
1-
1/
1)
#818
0-
0/
0)
1(
#819
1-
1/
1)
#820
0-
0/
10
0)
0(
1'
#821
1-
1/
1)
#822
0-
0/
0)
1(
#823
1-
1/
1)
#824
0-
0/
00
0)
0(
0'
1&
#825
1-
1/
1)
#826
0-
0/
0)
1(
#827
1-
1/
1)
#828
0-
0/
10
0)
0(
1'
#829
1-
1/
1)
#830
0-
0/
0)
1(
#831
1-
1/
1)
#832
0!
0-
0.
0/
00
01
12
0)
0(
0'
0&
0%
0$
1#
#833
1-
1/
1)
#834
0-
0/
0)
1(
#835
1-
1/
1)
#836
0-
0/
10
0)
0(
1'
#837
1-
1/
1)
#838
0-
0/
0)
1(
#839
1-
1/
1)
#840
0-
0/
00
0)
0(
0'
1&
#841
1-
1/
1)
#842
0-
0/
0)
1(
#843
1-
1/
1)
#844
0-
0/
10
0)
0(
1'
#845
1-
1/
1)
#846
0-
0/
0)
1(
#847
1-
1/
1)
#848
1!
0-
1.
0/
00
11
0)
0(
0'
0&
1%
#849
1-
1/
1)
#850
0-
0/
0)
1(
#851
1-
1/
1)
#852
0-
0/
10
0)
0(
1'
#853
1-
1/
1)
#854
0-
0/
0)
1(
#855
1-
1/
1)
#856
0-
0/
00
0)
0(
0'
1&
#857
1-
1/
1)
#858
0-
0/
0)
1(
#859
1-
1/
1)
#860
0-
0/
10
0)
0(
1'
#861
1-
1/
1)
#862
0-
0/
0)
1(
#863
1-
1/
1)
#864
0!
0-
0.
0/
00
01
0)
0(
0'
0&
0%
1$
#865
1-
1/
1)
#866
0-
0/
0)
1(
#867
1-
1/
1)
#868
0-
0/
10
0)
0(
1'
#869
1-
1/
1)
#870
0-
0/
0)
1(
#871
1-
1/
1)
#872
0-
0/
00
0)
0(
0'
1&
#873
1-
1/
1)
#874
0-
0/
0)
1(
#875
1-
1/
1)
#876
0-
0/
10
0)
0(
1'
#877
1-
1/
1)
#878
0-
0/
0)
1(
#879
1-
1/
1)
#880
1!
0-
1.
0/
00
11
0)
0(
0'
0&
1%
#881
1-
1/
1)
#882
0-
0/
0)
1(
#883
1-
1/
1)
#884
0-
0/
10
0)
0(
1'
#885
1-
1/
1)
#886
0-
0/
0)
1(
#887
1-
1/
1)
#888
0-
0/
00
0)
0(
0'
1&
#889
1-
1/
1)
#890
0-
0/
0)
1(
#891
1-
1/
1)
#892
0-
0/
10
0)
0(
1'
#893
1-
1/
1)
#894
0-
0/
0)
1(
#895
1-
1/
1)
#896
0!
0-
0.
0/
00
01
02
0)
0(
0'
0&
0%
0$
0#
1"
#897
1-
1/
1)
#898
0-
0/
0)
1(
#899
1-
1/
1)
#900
0-
0/
10
0)
0(
1'
#901
1-
1/
1)
#902
0-
0/
0)
1(
#903
1-
1/
1)
#904
0-
0/
00
0)
0(
0'
1&
#905
1-
1/
1)
#906
0-
0/
0)
1(
#907
1-
1/
1)
#908
0-
0/
10
0)
0(
1'
#909
1-
1/
1)
#910
0-
0/
0)
1(
#911
1-
1/
1)
#912
1!
0-
1.
0/
00
11
0)
0(
0'
0&
1%
#913
1-
1/
1)
#914
0-
0/
0)
1(
#915
1-
1/
1)
#916
0-
0/
10
0)
0(
1'
#917
1-
1/
1)
#918
0-
0/
0)
1(
#919
1-
1/
1)
#920
0-
0/
00
0)
0(
0'
1&
#921
1-
1/
1)
#922
0-
0/
0)
1(
#923
1-
1/
1)
#924
0-
0/
10
0)
0(
1'
#925
1-
1/
1)
#926
0-
0/
0)
1(
#927
1-
1/
1)
#928
0!
0-
0.
0/
00
01
0)
0(
0'
0&
0%
1$
#929
1-
1/
1)
#930
0-
0/
0)
1(
#931
1-
1/
1)
#932
0-
0/
10
0)
0(
1'
#933
1-
1/
1)
#934
0-
0/
0)
1(
#935
1-
1/
1)
#936
0-
0/
00
0)
0(
0'
1&
#937
1-
1/
1)
#938
0-
0/
0)
1(
#939
1-
1/
1)
#940
0-
0/
10
0)
0(
1'
#941
1-
1/
1)
#942
0-
0/
0)
1(
#943
1-
1/
1)
#944
1!
0-
1.
0/
00
11
0)
0(
0'
0&
1%
#945
1-
1/
1)
#946
0-
0/
0)
1(
#947
1-
1/
1)
#948
0-
0/
10
0)
0(
1'
#949
1-
1/
1)
#950
0-
0/
0)
1(
#951
1-
1/
1)
#952
0-
0/
00
0)
0(
0'
1&
#953
1-
1/
1)
#954
0-
0/
0)
1(
#955
1-
1/
1)
#956
0-
0/
10
0)
0(
1'
#957
1-
1/
1)
#958
0-
0/
0)
1(
#959
1-
1/
1)
#960
0!
0-
0.
0/
00
01
12
0)
0(
0'
0&
0%
0$
1#
#961
1-
1/
1)
#962
0-
0/
0)
1(
#963
1-
1/
1)
#964
0-
0/
10
0)
0(
1'
#965
1-
1/
1)
#966
0-
0/
0)
1(
#967
1-
1/
1)
#968
0-
0/
00
0)
0(
0'
1&
#969
1-
1/
1)
#970
0-
0/
0)
1(
#971
1-
1/
1)
#972
0-
0/
10
0)
0(
1'
#973
1-
1/
1)
#974
0-
0/
0)
1(
#975
1-
1/
1)
#976
1!
0-
1.
0/
00
11
0)
0(
0'
0&
1%
