Phase 1 Learning/MUX/MUX_2_1_example.v
module MUX_2_1 (S0,A,B,Y);
    
input S0,A,B;
output Y;

assign Y=((~S0)&A)+(S0&B);

endmodule

Phase 1 Learning/MUX/MUX_2_1_example_tb.v
`timescale 1ns/1ns
`include "MUX_2_1_example.v"

module MUX_2_1_example_tb;

reg A,B,S0;
wire Y;

MUX_2_1 uut(S0,A,B,Y);

initial begin
    $display("Time\tS0 A B  | Y");
    $monitor("%g\t%b %b %b | %b",$time,S0,A,B,Y);
end

initial begin
    A=0; B=0; S0=0; #10;
end

always #20 S0=~S0;
always #10 A=~A;
always #5 B=~B; 

initial begin
    #60 $finish;
end

initial begin
    $dumpfile("MUX_2_1_example.vcd");
    $dumpvars(0,MUX_2_1_example_tb);
end
    
endmodule

Phase 1 Learning/MUX/MUX_2_1_example.vcd
$date
	Sat Apr 18 00:01:22 2026
$end
$version
	Icarus Verilog
$end
$timescale
	1ns
$end
$scope module MUX_2_1_example_tb $end
$var wire 1 ! Y $end
$var reg 1 " A $end
$var reg 1 # B $end
$var reg 1 $ S0 $end
$scope module uut $end
$var wire 1 " A $end
$var wire 1 # B $end
$var wire 1 $ S0 $end
$var wire 1 ! Y $end
$upscope $end
$upscope $end
$enddefinitions $end
$comment Show the parameter values. $end
$dumpall
$end
#0
$dumpvars
0$
0#
0"
0!
$end
#5
1#
#10
1!
0#
1"
#15
1#
#20
0!
0#
0"
1$
#25
1!
1#
#30
0!
0#
1"
#35
1!
1#
#40
0!
0#
0"
0$
#45
1#
#50
1!
0#
1"
#55
1#
#60
0!
0#
0"
1$
